[
    {
        "albumNum": 4,
        "title": "발레리노"
    },
    {
        "albumNum": 3,
        "title": "광대"
    },
    {
        "albumNum": 7,
        "title": "나란 놈은 답은 너다"
    },
    {
        "albumNum": 7,
        "title": "회상"
    },
    {
        "albumNum": 3,
        "title": "내가 웃는게 아니야"
    },
    {
        "albumNum": 6,
        "title": "우리 지금 만나"
    },
    {
        "albumNum": 8,
        "title": "행복을 찾아서"
    },
    {
        "albumNum": 2,
        "title": "리쌍부르쓰"
    },
    {
        "albumNum": 6,
        "title": "일터"
    },
    {
        "albumNum": 7,
        "title": "독기"
    },
    {
        "albumNum": 4,
        "title": "누구를 위한 삶인가"
    },
    {
        "albumNum": 7,
        "title": "죽기전까지 날아야 하는 새"
    },
    {
        "albumNum": 4,
        "title": "영화처럼"
    },
    {
        "albumNum": 6,
        "title": "Carousel"
    },
    {
        "albumNum": 4,
        "title": "Sunshine"
    },
    {
        "albumNum": 6,
        "title": "To. LeeSSang"
    }
]